orgee/__init__.py
orgee/link.py
orgee/markup.py
orgee/orgnode.py
orgee/parse_org.py
orgee/properties.py
orgee/py.typed
orgee/tag.py
orgee/util.py
orgee-0.0.5.dist-info/METADATA
orgee-0.0.5.dist-info/WHEEL
orgee-0.0.5.dist-info/top_level.txt
orgee-0.0.5.dist-info/zip-safe
orgee-0.0.5.dist-info/RECORD
